pubplotlib/__init__.py
pubplotlib/_version.py
pubplotlib/formatter.py
pubplotlib/pubplotlib.py
pubplotlib/stylebuilder.py
pubplotlib/ticksetter.py
pubplotlib/assets/aanda.mplstyle
pubplotlib/assets/apj.mplstyle
pubplotlib/assets/original.mplstyle
pubplotlib/assets/pubplot.mplstyle
pubplotlib/assets/styles.yaml
pubplotlib-0.4.1.dist-info/licenses/LICENSE
pubplotlib-0.4.1.dist-info/METADATA
pubplotlib-0.4.1.dist-info/WHEEL
pubplotlib-0.4.1.dist-info/top_level.txt
pubplotlib-0.4.1.dist-info/RECORD
