Metadata-Version: 2.4
Name: pubplotlib
Version: 0.4.1
Summary: Make publication friendly plots easy!
Author-email: Pierpaolo Condò <pierpaolo.condo@gmail.com>, Michele Berretti <michele.berretti1999@gmail.com>
License:                     GNU GENERAL PUBLIC LICENSE
Project-URL: Homepage, https://github.com/pier-astro/PubPlotLib
Project-URL: Documentation, https://pubplotlib.readthedocs.io
Project-URL: Repository, https://github.com/pier-astro/PubPlotLib.git
Project-URL: Issues, https://github.com/pier-astro/PubPlotLib/issues
Project-URL: Changelog, https://github.com/pier-astro/PubPlotLib/releases
Keywords: matplotlib,publication,plot,figure,science
Classifier: Programming Language :: Python :: 3
Classifier: License :: OSI Approved :: GNU General Public License v3 (GPLv3)
Classifier: Operating System :: OS Independent
Requires-Python: >=3.2
License-File: LICENSE
Requires-Dist: matplotlib>=3.4
Requires-Dist: PyYAML>=5.3
Provides-Extra: dev
Requires-Dist: pytest>=7.0; extra == "dev"
Requires-Dist: sphinx>=7.0; extra == "dev"
Requires-Dist: sphinx-rtd-theme>=1.0; extra == "dev"
Requires-Dist: myst-parser>=0.18; extra == "dev"
Requires-Dist: docutils<=0.21.2,>=0.18.1; extra == "dev"
Dynamic: license-file
